ks/README.rst
ks/__init__.py
ks/ks_api/__init__.py
ks/ks_api/key_service_api/__init__.py
ks/ks_api/key_service_api/key_service_api.py
ks/ks_api/kms_apis/__init__.py
ks/ks_api/kms_apis/keywrapper.py
ks/ks_api/kms_apis/ks_aws.py
ks/ks_api/kms_apis/ks_local.py
ks/ks_api/kms_apis/ks_super.py
ks/ks_server/KS_URI.txt
ks/ks_server/__init__.py
ks/ks_server/key_server_api.py
ks/ks_server/ks_app.py
ks/ks_server/ks_server.py
ks/settings/__init__.py
ks/settings/mongo_settings.py
magen_key_service-1.9a6.data/scripts/ks_server.py
magen_key_service-1.9a6.dist-info/DESCRIPTION.rst
magen_key_service-1.9a6.dist-info/METADATA
magen_key_service-1.9a6.dist-info/RECORD
magen_key_service-1.9a6.dist-info/WHEEL
magen_key_service-1.9a6.dist-info/metadata.json
magen_key_service-1.9a6.dist-info/top_level.txt
