Metadata-Version: 2.0
Name: magen-key-service
Version: 1.9a6
Summary: Magen Key Service Package
Home-page: https://magengit.github.io/
Author: Reinaldo penno
Author-email: rapenno@gmail.com
License: Apache Software License
Platform: UNKNOWN
Classifier: Development Status :: 2 - Pre-Alpha
Classifier: Intended Audience :: Education
Classifier: Intended Audience :: Financial and Insurance Industry
Classifier: Intended Audience :: Healthcare Industry
Classifier: Intended Audience :: Legal Industry
Classifier: Topic :: Security
Classifier: License :: OSI Approved :: Apache Software License
Classifier: Programming Language :: Python :: 3.6
Requires-Dist: aniso8601 (>=1.2.1)
Requires-Dist: boto3 (>=1.4.4)
Requires-Dist: datadog (>=0.16.0)
Requires-Dist: PyJWT (>=1.5.2)
Requires-Dist: Flask (>=0.12.2)
Requires-Dist: flake8 (>=3.3.0)
Requires-Dist: pymongo (>=3.4.0)
Requires-Dist: pytest (>=3.1.3)
Requires-Dist: magen-utils (>=1.2a3)
Requires-Dist: magen-rest-service (>=1.3a5)
